alice_ai/__init__.py
alice_ai/console.py
alice_ai/main.py
alice_ai-1.0.1.dist-info/LICENSE
alice_ai-1.0.1.dist-info/METADATA
alice_ai-1.0.1.dist-info/WHEEL
alice_ai-1.0.1.dist-info/entry_points.txt
alice_ai-1.0.1.dist-info/top_level.txt
alice_ai-1.0.1.dist-info/RECORD
