Metadata-Version: 2.1
Name: alice-ai
Version: 1.0.1
Summary: Artificial Intelligence with python
Home-page: https://maestroal.github.io/alice/
Author: ['A. Maestro Alvardo']
Author-email: maestroalvardo@gmail.com
License: MIT License
Project-URL: Bug Reports, https://github.com/maestroal/alice/issues
Project-URL: Funding, https://donate.pypi.org
Project-URL: Source, https://github.com/maestroal/alice/
Keywords: Alice Python,Alice AI
Platform: UNKNOWN
Classifier: Intended Audience :: Developers
Classifier: Topic :: Software Development :: Build Tools
Classifier: License :: OSI Approved :: MIT License
Classifier: Programming Language :: Python :: 3
Classifier: Programming Language :: Python :: 3.6
Classifier: Programming Language :: Python :: 3.7
Classifier: Programming Language :: Python :: 3.8
Classifier: Programming Language :: Python :: 3.9
Classifier: Programming Language :: Python :: 3 :: Only
Requires-Python: >=3, <4
License-File: LICENSE
Requires-Dist: requests
Requires-Dist: playsound
Requires-Dist: gtts
Requires-Dist: SpeechRecognition
Requires-Dist: pyttsx3
